vbjax_dynamics/__init__.py
vbjax_dynamics/loops.py
vbjax_dynamics/utils.py
vbjax_dynamics-0.1.0.dist-info/licenses/LICENSE
vbjax_dynamics-0.1.0.dist-info/METADATA
vbjax_dynamics-0.1.0.dist-info/WHEEL
vbjax_dynamics-0.1.0.dist-info/top_level.txt
vbjax_dynamics-0.1.0.dist-info/RECORD
