Metadata-Version: 2.4
Name: vbjax_dynamics
Version: 0.1.0
Summary: JAX-based integrators for ODEs, DDEs, SDEs, and SDDEs
Author-email: Abolfazl Ziaeemehr <a.ziaeemehr@gmail.com>
License: MIT
Project-URL: Homepage, https://github.com/ziaeemehr/vbjax_dynamics
Project-URL: Documentation, https://vbjax-dynamics.readthedocs.io
Project-URL: Repository, https://github.com/ziaeemehr/vbjax_dynamics
Keywords: jax,ode,dde,sde,sdde,integrator,dynamics
Classifier: Development Status :: 3 - Alpha
Classifier: Intended Audience :: Science/Research
Classifier: License :: OSI Approved :: MIT License
Classifier: Programming Language :: Python :: 3
Classifier: Programming Language :: Python :: 3.9
Classifier: Programming Language :: Python :: 3.10
Classifier: Programming Language :: Python :: 3.11
Classifier: Topic :: Scientific/Engineering :: Mathematics
Requires-Python: >=3.9
License-File: LICENSE
Requires-Dist: jax>=0.4.0
Requires-Dist: jaxlib>=0.4.0
Requires-Dist: numpy>=1.20.0
Provides-Extra: dev
Requires-Dist: pytest>=7.0; extra == "dev"
Requires-Dist: pytest-cov>=4.0; extra == "dev"
Requires-Dist: black>=23.0; extra == "dev"
Requires-Dist: flake8>=6.0; extra == "dev"
Requires-Dist: mypy>=1.0; extra == "dev"
Requires-Dist: scipy>=1.9.0; extra == "dev"
Requires-Dist: matplotlib>=3.5.0; extra == "dev"
Provides-Extra: docs
Requires-Dist: sphinx>=5.0; extra == "docs"
Requires-Dist: sphinx-rtd-theme>=1.0; extra == "docs"
Dynamic: license-file
